apachetika/__init__.py
apachetika/data/tika-app.jar
apachetika/extract/__init__.py
python_apachetika-2.6.1.dist-info/LICENSE.txt
python_apachetika-2.6.1.dist-info/METADATA
python_apachetika-2.6.1.dist-info/WHEEL
python_apachetika-2.6.1.dist-info/top_level.txt
python_apachetika-2.6.1.dist-info/RECORD
